{
  "Schema": "[Person]",
  "Name": "[Address]",
  "CompressionType": "NONE",
  "OldName": "",
  "Columns": [
    {
      "Name": "[AddressID]",
      "DataType": "INT IDENTITY(1, 1) NOT FOR REPLICATION",
      "Nullable": false,
      "Persisted": false,
      "Sparse": false,
      "Collation": "",
      "DataMaskFunction": "",
      "OldName": ""
    },
    {
      "Name": "[AddressLine1]",
      "DataType": "NVARCHAR(60)",
      "Nullable": false,
      "Persisted": false,
      "Sparse": false,
      "Collation": "",
      "DataMaskFunction": "",
      "OldName": ""
    },
    {
      "Name": "[AddressLine2]",
      "DataType": "NVARCHAR(60)",
      "Nullable": true,
      "Persisted": false,
      "Sparse": false,
      "Collation": "",
      "DataMaskFunction": "",
      "OldName": ""
    },
    {
      "Name": "[City]",
      "DataType": "NVARCHAR(30)",
      "Nullable": false,
      "Persisted": false,
      "Sparse": false,
      "Collation": "",
      "DataMaskFunction": "",
      "OldName": ""
    },
    {
      "Name": "[ModifiedDate]",
      "DataType": "DATETIME",
      "Nullable": false,
      "Default": "getdate()",
      "Persisted": false,
      "Sparse": false,
      "Collation": "",
      "DataMaskFunction": "",
      "OldName": ""
    },
    {
      "Name": "[PostalCode]",
      "DataType": "NVARCHAR(15)",
      "Nullable": false,
      "Persisted": false,
      "Sparse": false,
      "Collation": "",
      "DataMaskFunction": "",
      "OldName": ""
    },
    {
      "Name": "[rowguid]",
      "DataType": "UNIQUEIDENTIFIER ROWGUIDCOL",
      "Nullable": false,
      "Default": "newid()",
      "Persisted": false,
      "Sparse": false,
      "Collation": "",
      "DataMaskFunction": "",
      "OldName": ""
    },
    {
      "Name": "[SpatialLocation]",
      "DataType": "GEOGRAPHY",
      "Nullable": true,
      "Persisted": false,
      "Sparse": false,
      "Collation": "",
      "DataMaskFunction": "",
      "OldName": ""
    },
    {
      "Name": "[StateProvinceID]",
      "DataType": "INT",
      "Nullable": false,
      "Persisted": false,
      "Sparse": false,
      "Collation": "",
      "DataMaskFunction": "",
      "OldName": ""
    }
  ],
  "Indexes": [
    {
      "Name": "[AK_Address_rowguid]",
      "CompressionType": "NONE",
      "PrimaryKey": false,
      "Unique": true,
      "UniqueConstraint": false,
      "Clustered": false,
      "ColumnStore": false,
      "FillFactor": 0,
      "IndexColumns": "[rowguid]"
    },
    {
      "Name": "[IX_Address_AddressLine1_AddressLine2_City_StateProvinceID_PostalCode]",
      "CompressionType": "NONE",
      "PrimaryKey": false,
      "Unique": true,
      "UniqueConstraint": false,
      "Clustered": false,
      "ColumnStore": false,
      "FillFactor": 0,
      "IndexColumns": "[AddressLine1],[AddressLine2],[City],[StateProvinceID],[PostalCode]"
    },
    {
      "Name": "[IX_Address_StateProvinceID]",
      "CompressionType": "NONE",
      "PrimaryKey": false,
      "Unique": false,
      "UniqueConstraint": false,
      "Clustered": false,
      "ColumnStore": false,
      "FillFactor": 0,
      "IndexColumns": "[StateProvinceID]"
    },
    {
      "Name": "[PK_Address_AddressID]",
      "CompressionType": "NONE",
      "PrimaryKey": true,
      "Unique": true,
      "UniqueConstraint": false,
      "Clustered": true,
      "ColumnStore": false,
      "FillFactor": 0,
      "IndexColumns": "[AddressID]"
    }
  ],
  "ForeignKeys": [
    {
      "Name": "[FK_Address_StateProvince_StateProvinceID]",
      "Columns": "[StateProvinceID]",
      "RelatedTableSchema": "[Person]",
      "RelatedTable": "[StateProvince]",
      "RelatedColumns": "[StateProvinceID]",
      "DeleteAction": "NO ACTION",
      "UpdateAction": "NO ACTION"
    }
  ]
}
