{
  "Schema": "[Person]",
  "Name": "[EmailAddress]",
  "CompressionType": "NONE",
  "OldName": "",
  "Columns": [
    {
      "Name": "[BusinessEntityID]",
      "DataType": "INT",
      "Nullable": false,
      "Persisted": false,
      "Sparse": false,
      "Collation": "",
      "DataMaskFunction": "",
      "OldName": ""
    },
    {
      "Name": "[EmailAddress]",
      "DataType": "NVARCHAR(50)",
      "Nullable": true,
      "Persisted": false,
      "Sparse": false,
      "Collation": "",
      "DataMaskFunction": "",
      "OldName": ""
    },
    {
      "Name": "[EmailAddressID]",
      "DataType": "INT IDENTITY(1, 1)",
      "Nullable": false,
      "Persisted": false,
      "Sparse": false,
      "Collation": "",
      "DataMaskFunction": "",
      "OldName": ""
    },
    {
      "Name": "[ModifiedDate]",
      "DataType": "DATETIME",
      "Nullable": false,
      "Default": "getdate()",
      "Persisted": false,
      "Sparse": false,
      "Collation": "",
      "DataMaskFunction": "",
      "OldName": ""
    },
    {
      "Name": "[rowguid]",
      "DataType": "UNIQUEIDENTIFIER ROWGUIDCOL",
      "Nullable": false,
      "Default": "newid()",
      "Persisted": false,
      "Sparse": false,
      "Collation": "",
      "DataMaskFunction": "",
      "OldName": ""
    }
  ],
  "Indexes": [
    {
      "Name": "[IX_EmailAddress_EmailAddress]",
      "CompressionType": "NONE",
      "PrimaryKey": false,
      "Unique": false,
      "UniqueConstraint": false,
      "Clustered": false,
      "ColumnStore": false,
      "FillFactor": 0,
      "IndexColumns": "[EmailAddress]"
    },
    {
      "Name": "[PK_EmailAddress_BusinessEntityID_EmailAddressID]",
      "CompressionType": "NONE",
      "PrimaryKey": true,
      "Unique": true,
      "UniqueConstraint": false,
      "Clustered": true,
      "ColumnStore": false,
      "FillFactor": 0,
      "IndexColumns": "[BusinessEntityID],[EmailAddressID]"
    }
  ],
  "ForeignKeys": [
    {
      "Name": "[FK_EmailAddress_Person_BusinessEntityID]",
      "Columns": "[BusinessEntityID]",
      "RelatedTableSchema": "[Person]",
      "RelatedTable": "[Person]",
      "RelatedColumns": "[BusinessEntityID]",
      "DeleteAction": "NO ACTION",
      "UpdateAction": "NO ACTION"
    }
  ]
}
