{
  "Schema": "[Sales]",
  "Name": "[Currency]",
  "CompressionType": "NONE",
  "Columns": [
    {
      "Name": "[CurrencyCode]",
      "DataType": "NCHAR(3)",
      "Nullable": false,
      "Persisted": false,
      "Sparse": false,
      "Collation": "",
      "DataMaskFunction": "",
      "ExtendedProperties": {
        "MS_Description": "The ISO code for the Currency."
      }
    },
    {
      "Name": "[ModifiedDate]",
      "DataType": "DATETIME",
      "Nullable": false,
      "Default": "getdate()",
      "Persisted": false,
      "Sparse": false,
      "Collation": "",
      "DataMaskFunction": "",
      "ExtendedProperties": {
        "MS_Description": "Date and time the record was last updated."
      }
    },
    {
      "Name": "[Name]",
      "DataType": "NAME",
      "Nullable": false,
      "Persisted": false,
      "Sparse": false,
      "Collation": "",
      "DataMaskFunction": "",
      "ExtendedProperties": {
        "MS_Description": "Currency name."
      }
    }
  ],
  "Indexes": [
    {
      "Name": "[AK_Currency_Name]",
      "CompressionType": "NONE",
      "PrimaryKey": false,
      "Unique": true,
      "UniqueConstraint": false,
      "Clustered": false,
      "ColumnStore": false,
      "FillFactor": 0,
      "IndexColumns": "[Name]",
      "ExtendedProperties": {
        "MS_Description": "Unique nonclustered index."
      }
    },
    {
      "Name": "[PK_Currency_CurrencyCode]",
      "CompressionType": "NONE",
      "PrimaryKey": true,
      "Unique": true,
      "UniqueConstraint": false,
      "Clustered": true,
      "ColumnStore": false,
      "FillFactor": 0,
      "IndexColumns": "[CurrencyCode]",
      "ExtendedProperties": {
        "MS_Description": "Primary key (clustered) constraint Clustered index created by a primary key constraint."
      }
    }
  ],
  "ExtendedProperties": {
    "MS_Description": "Lookup table containing standard ISO currencies."
  }
}
