{
  "Schema": "[Sales]",
  "Name": "[CountryRegionCurrency]",
  "CompressionType": "NONE",
  "OldName": "",
  "Columns": [
    {
      "Name": "[CountryRegionCode]",
      "DataType": "NVARCHAR(3)",
      "Nullable": false,
      "Persisted": false,
      "Sparse": false,
      "Collation": "",
      "DataMaskFunction": "",
      "OldName": ""
    },
    {
      "Name": "[CurrencyCode]",
      "DataType": "NCHAR(3)",
      "Nullable": false,
      "Persisted": false,
      "Sparse": false,
      "Collation": "",
      "DataMaskFunction": "",
      "OldName": ""
    },
    {
      "Name": "[ModifiedDate]",
      "DataType": "DATETIME",
      "Nullable": false,
      "Default": "getdate()",
      "Persisted": false,
      "Sparse": false,
      "Collation": "",
      "DataMaskFunction": "",
      "OldName": ""
    }
  ],
  "Indexes": [
    {
      "Name": "[IX_CountryRegionCurrency_CurrencyCode]",
      "CompressionType": "NONE",
      "PrimaryKey": false,
      "Unique": false,
      "UniqueConstraint": false,
      "Clustered": false,
      "ColumnStore": false,
      "FillFactor": 0,
      "IndexColumns": "[CurrencyCode]"
    },
    {
      "Name": "[PK_CountryRegionCurrency_CountryRegionCode_CurrencyCode]",
      "CompressionType": "NONE",
      "PrimaryKey": true,
      "Unique": true,
      "UniqueConstraint": false,
      "Clustered": true,
      "ColumnStore": false,
      "FillFactor": 0,
      "IndexColumns": "[CountryRegionCode],[CurrencyCode]"
    }
  ],
  "ForeignKeys": [
    {
      "Name": "[FK_CountryRegionCurrency_CountryRegion_CountryRegionCode]",
      "Columns": "[CountryRegionCode]",
      "RelatedTableSchema": "[Person]",
      "RelatedTable": "[CountryRegion]",
      "RelatedColumns": "[CountryRegionCode]",
      "DeleteAction": "NO ACTION",
      "UpdateAction": "NO ACTION"
    },
    {
      "Name": "[FK_CountryRegionCurrency_Currency_CurrencyCode]",
      "Columns": "[CurrencyCode]",
      "RelatedTableSchema": "[Sales]",
      "RelatedTable": "[Currency]",
      "RelatedColumns": "[CurrencyCode]",
      "DeleteAction": "NO ACTION",
      "UpdateAction": "NO ACTION"
    }
  ]
}
